{
  "subtitles": [],
  "orientation": [
    {
      "start": 0,
      "end": 19.845937,
      "orientations": [
        0
      ]
    },
    {
      "start": 19.845937,
      "end": 35.232,
      "orientations": [
        0
      ]
    },
    {
      "start": 35.232,
      "end": 49.406319,
      "orientations": [
        0,
        4.196971482272848
      ]
    },
    {
      "start": 49.406319,
      "end": 80.688323,
      "orientations": [
        0.19512236536463967,
        3.280264534809546
      ]
    },
    {
      "start": 80.688323,
      "end": 102.603334,
      "orientations": [
        -0.6909049989864502,
        1.4799847490461557
      ]
    },
    {
      "start": 102.603334,
      "end": 136.015522,
      "orientations": [
        -0.7191301850370255,
        1.2063224518349207,
        4.387185121026564
      ]
    },
    {
      "start": 136.015522,
      "end": 156.511686,
      "orientations": [
        -1.451759386290913,
        0.7890797116658508,
        -0.1227184448639631
      ]
    },
    {
      "start": 156.511686,
      "end": 179.148821,
      "orientations": [
        -0.007363097635467941
      ]
    },
    {
      "start": 179.148821,
      "end": 191.48205,
      "orientations": [
        -0.007363097635467941
      ]
    },
    {
      "start": 191.48205,
      "end": 214.696214,
      "orientations": [
        -0.607456356923564,
        2.008901277497054
      ]
    },
    {
      "start": 214.696214,
      "end": 235.3816,
      "orientations": [
        0.176714576438731,
        -1.0431069649870426
      ]
    },
    {
      "start": 235.3816,
      "orientations": [
        0.9756117609365146,
        -0.41601560779453184
      ]
    },
    {
      "start": 235.412208,
      "end": 289.601985,
      "orientations": [
        -0.5454153855822894,
        0.9970193193804396
      ]
    },
    {
      "start": 289.601985,
      "end": 293.8,
      "orientations": [
        -0.0021816668565890485
      ]
    }
  ],
  "videos": [
    {
      "fn": "videos/volcano.mp4",
      "stereo": false,
      "name": "main"
    },
    {
      "fn": "videos/volcano.mp4",
      "stereo": false,
      "name": "regular-cuts"
    }
  ]
}